a_pandas_ex_enumerate_groups/LICENSE
a_pandas_ex_enumerate_groups/README.MD
a_pandas_ex_enumerate_groups/__init__.py
a_pandas_ex_enumerate_groups/requirements.txt
a_pandas_ex_enumerate_groups/thirdparty.json
a_pandas_ex_enumerate_groups-0.12.dist-info/LICENSE.rst
a_pandas_ex_enumerate_groups-0.12.dist-info/METADATA
a_pandas_ex_enumerate_groups-0.12.dist-info/WHEEL
a_pandas_ex_enumerate_groups-0.12.dist-info/top_level.txt
a_pandas_ex_enumerate_groups-0.12.dist-info/RECORD
